upd_noIP/__init__.py
upd_noIP/agents.py
upd_noIP/cli.py
upd_noIP/noip.py
upd_noIP-0.1.2.dist-info/LICENSE
upd_noIP-0.1.2.dist-info/METADATA
upd_noIP-0.1.2.dist-info/WHEEL
upd_noIP-0.1.2.dist-info/entry_points.txt
upd_noIP-0.1.2.dist-info/top_level.txt
upd_noIP-0.1.2.dist-info/RECORD
