Metadata-Version: 2.1
Name: upd_noIP
Version: 0.1.2
Summary: Модуль для автоматичного оновлення IP на No-IP (завжди онлайн)
Home-page: https://github.com/DepyXa/upd_noIP
Author: Дмитро Колоднянський
Author-email: gosdepyxa@gmail.com
Classifier: Programming Language :: Python :: 3
Classifier: License :: OSI Approved :: MIT License
Classifier: Operating System :: OS Independent
Requires-Python: >=3.7
License-File: LICENSE
Requires-Dist: aiohttp >=3.8.0
